cpython_lldb.py
cpython_lldb-0.3.3.dist-info/METADATA
cpython_lldb-0.3.3.dist-info/WHEEL
cpython_lldb-0.3.3.dist-info/licenses/LICENSE
cpython_lldb-0.3.3.dist-info/RECORD
