Metadata-Version: 2.4
Name: cpython-lldb
Version: 0.3.3
Summary: LLDB extension for debugging Python programs
License: MIT
License-File: LICENSE
Keywords: debugging,lldb,cpython
Author: Roman Podoliaka
Author-email: roman.podoliaka@gmail.com
Requires-Python: >=3.7,<4.0
Classifier: License :: OSI Approved :: MIT License
Classifier: Programming Language :: Python :: 3
Classifier: Programming Language :: Python :: 3.7
Classifier: Programming Language :: Python :: 3.8
Classifier: Programming Language :: Python :: 3.9
Classifier: Programming Language :: Python :: 3.10
Classifier: Programming Language :: Python :: 3.11
Classifier: Programming Language :: Python :: 3.12
Classifier: Programming Language :: Python :: 3.13
Classifier: Programming Language :: Python :: 3.14
Project-URL: Homepage, https://github.com/malor/cpython-lldb
Project-URL: Repository, https://github.com/malor/cpython-lldb
